{
  "centrality_score": 0.9975460122699387,
  "classification": "INTERNAL",
  "confidence": "EXTRACTED",
  "content": {
    "language": "python",
    "manifest": "pyproject.toml",
    "package": "fastapi",
    "summary": "Depends on fastapi ^0.100.0",
    "version": "^0.100.0"
  },
  "created": "2026-04-19T17:26:31Z",
  "created_by": "cartographer",
  "id": "fact-aca280d8dadf",
  "landmark": false,
  "lifecycle": "permanent",
  "promotion_state": "draft",
  "provenance": {
    "trigger_event": "bootstrap.scan"
  },
  "scope": "project",
  "tags": [
    "dependency",
    "python",
    "bootstrap"
  ],
  "type": "fact",
  "updated": "2026-04-19T17:26:31Z",
  "updated_by": "cartographer"
}
