{
  "centrality_score": 0.9975460122699387,
  "classification": "INTERNAL",
  "confidence": "EXTRACTED",
  "content": {
    "kind": "typedef",
    "language": "c",
    "summary": "c typedef: Config",
    "symbol": "Config"
  },
  "created": "2026-04-19T17:26:31Z",
  "created_by": "cartographer",
  "id": "pat-0d1633154181",
  "landmark": false,
  "lifecycle": "permanent",
  "promotion_state": "draft",
  "provenance": {
    "trigger_event": "bootstrap.scan"
  },
  "scope": "project",
  "tags": [
    "c",
    "typedef",
    "ast",
    "bootstrap",
    "pkg-testdata"
  ],
  "type": "pattern",
  "updated": "2026-04-19T17:26:31Z",
  "updated_by": "cartographer"
}
