{
  "centrality_score": 0.9975460122699387,
  "classification": "INTERNAL",
  "confidence": "EXTRACTED",
  "content": {
    "doc": "Walk walks up from cwd and returns every ancestor directory that contains a .leo/ subdirectory, ordered nearest-first. It stops at $HOME (exclusive) — it never walks above the user's home directory.  Symlinks are skipped: if a directory entry is a symlink, it is not followed. This prevents cycles and avoids traversing unexpected paths.",
    "kind": "function",
    "language": "go",
    "name": "Walk",
    "summary": "Function: Walk — Walk walks up from cwd and returns every ancestor directory that contains a .leo/ subdirectory, o..."
  },
  "created": "2026-04-19T17:26:31Z",
  "created_by": "cartographer",
  "id": "pat-e14fa8f34687",
  "landmark": false,
  "lifecycle": "permanent",
  "promotion_state": "draft",
  "provenance": {
    "trigger_event": "bootstrap.scan"
  },
  "scope": "project",
  "tags": [
    "go",
    "function",
    "ast",
    "bootstrap",
    "pkg-scope"
  ],
  "type": "pattern",
  "updated": "2026-04-19T17:26:31Z",
  "updated_by": "cartographer"
}
